termiredy/__init__.py
termiredy/cli.py
termiredy/notifications.py
termiredy-0.1.0.dist-info/METADATA
termiredy-0.1.0.dist-info/WHEEL
termiredy-0.1.0.dist-info/entry_points.txt
termiredy-0.1.0.dist-info/top_level.txt
termiredy-0.1.0.dist-info/RECORD
