Metadata-Version: 2.4
Name: termiredy
Version: 0.1.0
Summary: A terminal tool that notifies you when your task is done.
Author-email: Bryan Wang <bryan54045@gmail.com>
License: MIT
Project-URL: Homepage, https://github.com/BryanSapo/Termiredy
Requires-Python: >=3.8
